infdb/Infdb.py
infdb/InfdbClient.py
infdb/InfdbConfig.py
infdb/InfdbLogger.py
infdb/__init__.py
infdb/utils.py
infdb-0.1.0.dist-info/licenses/LICENSE
infdb-0.1.0.dist-info/METADATA
infdb-0.1.0.dist-info/WHEEL
infdb-0.1.0.dist-info/top_level.txt
infdb-0.1.0.dist-info/RECORD
