Metadata-Version: 2.4
Name: infdb
Version: 0.1.0
Summary: InfDB wrapper for python
Author-email: Patrick Buchenberg <patrick.buchenberg@tum.de>
License: MIT
Project-URL: Homepage, https://github.com/tum-ens/InfDB
Project-URL: Issues, https://github.com/tum-ens/InfDB/issues
Project-URL: Documentation, https://infdb.readthedocs.io
Classifier: Development Status :: 3 - Alpha
Classifier: Intended Audience :: Science/Research
Classifier: License :: OSI Approved :: MIT License
Classifier: Programming Language :: Python :: 3
Classifier: Programming Language :: Python :: 3.10
Classifier: Programming Language :: Python :: 3.11
Classifier: Programming Language :: Python :: 3.12
Classifier: Programming Language :: Python :: 3.13
Classifier: Operating System :: OS Independent
Classifier: Topic :: Scientific/Engineering
Requires-Python: >=3.9
License-File: LICENSE
Requires-Dist: psycopg2-binary
Requires-Dist: PyYAML
Requires-Dist: dotenv
Requires-Dist: SQLAlchemy
Dynamic: license-file
